wspg/__init__.py
wspg/application.py
wspg/endpoint.py
wspg/errors.py
wspg/jwt_issuer.py
wspg/query_rules_rule_set_parser.py
wspg/session.py
wspg-1.17.dist-info/LICENSE
wspg-1.17.dist-info/METADATA
wspg-1.17.dist-info/WHEEL
wspg-1.17.dist-info/entry_points.txt
wspg-1.17.dist-info/top_level.txt
wspg-1.17.dist-info/RECORD
