Metadata-Version: 2.1
Name: wspg
Version: 1.17
Summary: Expose PostgreSQL databases via a websocket
Home-page: https://bitbucket.org/gclinch/wspg
Author: Graham Clinch
Author-email: g.clinch@lancaster.ac.uk
License: Apache License, Version 2.0
Platform: UNKNOWN
Classifier: Development Status :: 5 - Production/Stable
Classifier: License :: OSI Approved :: Apache Software License
Classifier: Topic :: Database
Requires-Dist: aiopg
Requires-Dist: jquery-querybuilder-psycopg2
Requires-Dist: PyJWT
Requires-Dist: psycopg2
Requires-Dist: websockets
